ITTR_pytorch/ITTR_pytorch.py
ITTR_pytorch/__init__.py
ITTR_pytorch-0.0.4.dist-info/LICENSE
ITTR_pytorch-0.0.4.dist-info/METADATA
ITTR_pytorch-0.0.4.dist-info/WHEEL
ITTR_pytorch-0.0.4.dist-info/top_level.txt
ITTR_pytorch-0.0.4.dist-info/RECORD
